pypkgs_jk/__init__.py
pypkgs_jk/pypkgs_jk.py
pypkgs_jk-0.1.0.dist-info/LICENSE
pypkgs_jk-0.1.0.dist-info/WHEEL
pypkgs_jk-0.1.0.dist-info/METADATA
pypkgs_jk-0.1.0.dist-info/RECORD
