Metadata-Version: 2.1
Name: pypkgs-jk
Version: 0.1.0
Summary: Toy Python package for UBC DSCI 524
License: MIT
Author: Junghoo Kim
Author-email: jkim222383@gmail.com
Requires-Python: >=3.8,<4.0
Classifier: License :: OSI Approved :: MIT License
Classifier: Programming Language :: Python :: 3
Classifier: Programming Language :: Python :: 3.8
Classifier: Programming Language :: Python :: 3.9
Requires-Dist: altair (>=4.1.0,<5.0.0)
